pytest_subunit.py
pytest_subunit-0.0.11.dist-info/LICENSE
pytest_subunit-0.0.11.dist-info/METADATA
pytest_subunit-0.0.11.dist-info/WHEEL
pytest_subunit-0.0.11.dist-info/entry_points.txt
pytest_subunit-0.0.11.dist-info/top_level.txt
pytest_subunit-0.0.11.dist-info/RECORD
